colav_bridge/__init__.py
colav_bridge/proto_to_ros/__init__.py
colav_bridge/proto_to_ros/parse_agent_update.py
colav_bridge/proto_to_ros/parse_map_metadata.py
colav_bridge/proto_to_ros/parse_mission_request.py
colav_bridge/proto_to_ros/parse_obstacles_update.py
colav_bridge/proto_to_ros/utils/__init__.py
colav_bridge/proto_to_ros/utils/parse_dynamic_obstacle_geometry.py
colav_bridge/proto_to_ros/utils/parse_point.py
colav_bridge/proto_to_ros/utils/parse_polygon.py
colav_bridge/proto_to_ros/utils/parse_pose.py
colav_bridge/proto_to_ros/utils/parse_stamp.py
colav_bridge/proto_to_ros/utils/parse_static_obstacle_geometry.py
colav_bridge/proto_to_ros/utils/parse_vessel.py
colav_bridge/proto_to_ros/utils/parse_waypoints.py
colav_bridge/ros_to_proto/__init__.py
colav_bridge/ros_to_proto/parse_controller_feedback.py
colav_bridge-0.1.2.dist-info/METADATA
colav_bridge-0.1.2.dist-info/WHEEL
colav_bridge-0.1.2.dist-info/licenses/LICENSE
colav_bridge-0.1.2.dist-info/RECORD
