Metadata-Version: 2.4
Name: colav-bridge
Version: 0.1.2
Summary: A pkg for converting ROS2 [colav-interfaces](https://github.com/Artemis-QUB-COLAV/colav-interfaces) to [colav-protobuf](https://github.com/Artemis-QUB-COLAV/colav-protobuf) and vice versa
Project-URL: Documentation, https://github.com/Artemis-QUB-COLAV/colav-bridge#readme
Project-URL: Issues, https://github.com/Artemis-QUB-COLAV/colav-bridge/issues
Project-URL: Source, https://github.com/Artemis-QUB-COLAV/colav-bridge
Author-email: Ryan McKee <r.mckee@qub.ac.uk>
License-Expression: MIT
License-File: LICENSE
Keywords: bridge,colav,interfaces,protobuf,ros2
Classifier: Development Status :: 4 - Beta
Classifier: Programming Language :: Python
Classifier: Programming Language :: Python :: 3.8
Classifier: Programming Language :: Python :: 3.9
Classifier: Programming Language :: Python :: 3.10
Classifier: Programming Language :: Python :: 3.11
Classifier: Programming Language :: Python :: 3.12
Classifier: Programming Language :: Python :: Implementation :: CPython
Classifier: Programming Language :: Python :: Implementation :: PyPy
Requires-Python: >=3.8
Requires-Dist: colav-protobuf-utils==0.2.0
Requires-Dist: hatch
